patchright/__init__.py
patchright/__main__.py
patchright/_repo_version.py
patchright/py.typed
patchright/_impl/__init__.py
patchright/_impl/_accessibility.py
patchright/_impl/_api_structures.py
patchright/_impl/_artifact.py
patchright/_impl/_assertions.py
patchright/_impl/_async_base.py
patchright/_impl/_browser.py
patchright/_impl/_browser_context.py
patchright/_impl/_browser_type.py
patchright/_impl/_cdp_session.py
patchright/_impl/_clock.py
patchright/_impl/_connection.py
patchright/_impl/_console_message.py
patchright/_impl/_dialog.py
patchright/_impl/_download.py
patchright/_impl/_driver.py
patchright/_impl/_element_handle.py
patchright/_impl/_errors.py
patchright/_impl/_event_context_manager.py
patchright/_impl/_fetch.py
patchright/_impl/_file_chooser.py
patchright/_impl/_frame.py
patchright/_impl/_glob.py
patchright/_impl/_greenlets.py
patchright/_impl/_har_router.py
patchright/_impl/_helper.py
patchright/_impl/_impl_to_api_mapping.py
patchright/_impl/_input.py
patchright/_impl/_js_handle.py
patchright/_impl/_json_pipe.py
patchright/_impl/_local_utils.py
patchright/_impl/_locator.py
patchright/_impl/_map.py
patchright/_impl/_network.py
patchright/_impl/_object_factory.py
patchright/_impl/_page.py
patchright/_impl/_path_utils.py
patchright/_impl/_playwright.py
patchright/_impl/_selectors.py
patchright/_impl/_set_input_files_helpers.py
patchright/_impl/_str_utils.py
patchright/_impl/_stream.py
patchright/_impl/_sync_base.py
patchright/_impl/_tracing.py
patchright/_impl/_transport.py
patchright/_impl/_video.py
patchright/_impl/_waiter.py
patchright/_impl/_web_error.py
patchright/_impl/_writable_stream.py
patchright/_impl/__pyinstaller/__init__.py
patchright/_impl/__pyinstaller/hook-playwright.async_api.py
patchright/_impl/__pyinstaller/hook-playwright.sync_api.py
patchright/async_api/__init__.py
patchright/async_api/_context_manager.py
patchright/async_api/_generated.py
patchright/driver/LICENSE
re_patchright-1.52.10.dist-info/METADATA
re_patchright-1.52.10.dist-info/WHEEL
re_patchright-1.52.10.dist-info/entry_points.txt
re_patchright-1.52.10.dist-info/top_level.txt
re_patchright-1.52.10.dist-info/RECORD
re_patchright-1.52.10.dist-info/licenses/LICENSE
