Metadata-Version: 2.4
Name: re-patchright
Version: 1.52.10
Summary: Undetected Python version of the Playwright testing and automation library tweaked for a specific logic.
Author: Microsoft Corporation, patched by github.com/Kaliiiiiiiiii-Vinyzu/ and tweaked by github.com/imamousenotacat/ 
License-Expression: Apache-2.0
Project-URL: homepage, https://github.com/imamousenotacat/re-patchright-python
Project-URL: Release notes, https://github.com/imamousenotacat/re-patchright-python/releases
Project-URL: Bug Reports, https://github.com/imamousenotacat/re-patchright-python/issues
Project-URL: homeSource Codepage, https://github.com/imamousenotacat/re-patchright-python
Classifier: Topic :: Software Development :: Testing
Classifier: Topic :: Internet :: WWW/HTTP :: Browsers
Classifier: Intended Audience :: Developers
Classifier: Programming Language :: Python :: 3
Classifier: Programming Language :: Python :: 3.9
Classifier: Programming Language :: Python :: 3.10
Classifier: Programming Language :: Python :: 3.11
Classifier: Programming Language :: Python :: 3.12
Classifier: Programming Language :: Python :: 3.13
Classifier: Operating System :: OS Independent
Requires-Python: >=3.9
License-File: LICENSE
Requires-Dist: pyee<14,>=13
Requires-Dist: greenlet<4.0.0,>=3.1.1
Dynamic: license-file
